Workbook

Sheet Budget
A1: Household Budget
B3: Earner 1 | E3: Earner 2 | H3: Household
A4: INCOME | B4: 0 | E4: 0 | H4: =B4+E4 -> 0
A5: FIXED EXPENSES
A6: Housing | B6: 0 | E6: 0 | H6: =B6+E6 -> 0
A7: Utilities | B7: 0 | E7: 0 | H7: =B7+E7 -> 0
A8: Transport | B8: 0 | E8: 0 | H8: =B8+E8 -> 0
A9: Groceries | B9: 0 | E9: 0 | H9: =B9+E9 -> 0
A10: Insurance | B10: 0 | E10: 0 | H10: =B10+E10 -> 0
A11: Subscriptions | B11: 0 | E11: 0 | H11: =B11+E11 -> 0
A12: Kids | B12: 0 | E12: 0 | H12: =B12+E12 -> 0
A13: Other | B13: 0 | E13: 0 | H13: =B13+E13 -> 0
A14: Total Fixed Expenses | B14: =SUM(B5:B12) -> 0 | E14: =SUM(E5:E12) -> 0 | H14: =B14+E14 -> 0
A15: INVESTMENTS | B15: 0 | E15: 0 | H15: =B15+E15 -> 0
A16: DEBT PAYMENTS | B16: 0 | E16: 0 | H16: =B16+E16 -> 0
A18: Available for Snowball | B18: =B4-B14-B15-B16 -> 0 | E18: =E4-E14-E15-E16 -> 0 | H18: =B18+E18 -> 0
A19: Living Buffer | B19: 0 | E19: 0 | H19: =B19+E19 -> 0
A20: Conscious Spending | B20: 0 | E20: 0 | H20: =B20+E20 -> 0
A21: Net Snowball Power | B21: =B18-B19-B20 -> 0 | E21: =E18-E19-E20 -> 0 | H21: =B21+E21 -> 0

Sheet Debt Tracker
A1: Debt Tracker
A3: # | B3: Creditor | C3: Owner | D3: Balance | E3: Rate (%) | F3: Min Payment | G3: Monthly Interest | H3: Priority | I3: Phase | J3: Status
A4: 1 | D4: 0 | E4: 0 | F4: 0 | G4: =IF(D4=0,0,D4*E4/12/100) -> 0
A5: 2 | D5: 0 | E5: 0 | F5: 0 | G5: =IF(D5=0,0,D5*E5/12/100) -> 0
A6: 3 | D6: 0 | E6: 0 | F6: 0 | G6: =IF(D6=0,0,D6*E6/12/100) -> 0
A7: 4 | D7: 0 | E7: 0 | F7: 0 | G7: =IF(D7=0,0,D7*E7/12/100) -> 0
A8: 5 | D8: 0 | E8: 0 | F8: 0 | G8: =IF(D8=0,0,D8*E8/12/100) -> 0
A9: 6 | D9: 0 | E9: 0 | F9: 0 | G9: =IF(D9=0,0,D9*E9/12/100) -> 0
A10: 7 | D10: 0 | E10: 0 | F10: 0 | G10: =IF(D10=0,0,D10*E10/12/100) -> 0
A11: 8 | D11: 0 | E11: 0 | F11: 0 | G11: =IF(D11=0,0,D11*E11/12/100) -> 0
A12: 9 | D12: 0 | E12: 0 | F12: 0 | G12: =IF(D12=0,0,D12*E12/12/100) -> 0
A13: 10 | D13: 0 | E13: 0 | F13: 0 | G13: =IF(D13=0,0,D13*E13/12/100) -> 0
A14: 11 | D14: 0 | E14: 0 | F14: 0 | G14: =IF(D14=0,0,D14*E14/12/100) -> 0
A15: 12 | D15: 0 | E15: 0 | F15: 0 | G15: =IF(D15=0,0,D15*E15/12/100) -> 0
A16: TOTALS | D16: =SUM(D4:D15) -> 0 | F16: =SUM(F4:F15) -> 0 | G16: =SUM(G4:G15) -> 0

Sheet Interest Tracker
A1: Interest Tracker
A3: Current Monthly Interest by Debt
A4: Debt | B4: Monthly Interest
A5: =IF(COUNTA('Debt Tracker'!B4)>0,'Debt Tracker'!B4,"") | B5: =IF(COUNTA('Debt Tracker'!B4)>0,'Debt Tracker'!G4,"")
A6: =IF(COUNTA('Debt Tracker'!B5)>0,'Debt Tracker'!B5,"") | B6: =IF(COUNTA('Debt Tracker'!B5)>0,'Debt Tracker'!G5,"")
A7: =IF(COUNTA('Debt Tracker'!B6)>0,'Debt Tracker'!B6,"") | B7: =IF(COUNTA('Debt Tracker'!B6)>0,'Debt Tracker'!G6,"")
A8: =IF(COUNTA('Debt Tracker'!B7)>0,'Debt Tracker'!B7,"") | B8: =IF(COUNTA('Debt Tracker'!B7)>0,'Debt Tracker'!G7,"")
A9: =IF(COUNTA('Debt Tracker'!B8)>0,'Debt Tracker'!B8,"") | B9: =IF(COUNTA('Debt Tracker'!B8)>0,'Debt Tracker'!G8,"")
A10: =IF(COUNTA('Debt Tracker'!B9)>0,'Debt Tracker'!B9,"") | B10: =IF(COUNTA('Debt Tracker'!B9)>0,'Debt Tracker'!G9,"")
A11: =IF(COUNTA('Debt Tracker'!B10)>0,'Debt Tracker'!B10,"") | B11: =IF(COUNTA('Debt Tracker'!B10)>0,'Debt Tracker'!G10,"")
A12: =IF(COUNTA('Debt Tracker'!B11)>0,'Debt Tracker'!B11,"") | B12: =IF(COUNTA('Debt Tracker'!B11)>0,'Debt Tracker'!G11,"")
A13: =IF(COUNTA('Debt Tracker'!B12)>0,'Debt Tracker'!B12,"") | B13: =IF(COUNTA('Debt Tracker'!B12)>0,'Debt Tracker'!G12,"")
A14: =IF(COUNTA('Debt Tracker'!B13)>0,'Debt Tracker'!B13,"") | B14: =IF(COUNTA('Debt Tracker'!B13)>0,'Debt Tracker'!G13,"")
A15: =IF(COUNTA('Debt Tracker'!B14)>0,'Debt Tracker'!B14,"") | B15: =IF(COUNTA('Debt Tracker'!B14)>0,'Debt Tracker'!G14,"")
A16: =IF(COUNTA('Debt Tracker'!B15)>0,'Debt Tracker'!B15,"") | B16: =IF(COUNTA('Debt Tracker'!B15)>0,'Debt Tracker'!G15,"")
A18: Monthly Tracking
A19: Date | B19: Total Monthly Interest | C19: Annual Rate | D19: Change vs Baseline | E19: Cumulative Savings
A20: Baseline | B20: ='Debt Tracker'!G16 -> 0 | C20: =B20*12 -> 0 | D20: 0 | E20: 0

Sheet Goals
A1: Goals
A3: SHORT TERM (3-6 months)
B4: 0 | C4: 0 | D4: =B4-C4 -> 0
B5: 0 | C5: 0 | D5: =B5-C5 -> 0
B6: 0 | C6: 0 | D6: =B6-C6 -> 0
A7: MEDIUM TERM (6-24 months)
B8: 0 | C8: 0 | D8: =B8-C8 -> 0
B9: 0 | C9: 0 | D9: =B9-C9 -> 0
B10: 0 | C10: 0 | D10: =B10-C10 -> 0
A11: LONG TERM (2+ years)
B12: 0 | C12: 0 | D12: =B12-C12 -> 0
B13: 0 | C13: 0 | D13: =B13-C13 -> 0
B14: 0 | C14: 0 | D14: =B14-C14 -> 0

Sheet Snowball Forecast
A1: Snowball Forecast
A3: Debt | B3: Month 1 | C3: Month 2 | D3: Month 3 | E3: Month 4 | F3: Month 5 | G3: Month 6 | H3: Month 7 | I3: Month 8 | J3: Month 9 | K3: Month 10 | L3: Month 11 | M3: Month 12 | N3: Month 13 | O3: Month 14 | P3: Month 15 | Q3: Month 16 | R3: Month 17 | S3: Month 18 | T3: Month 19 | U3: Month 20 | V3: Month 21 | W3: Month 22 | X3: Month 23 | Y3: Month 24 | Z3: Month 25 | AA3: Month 26 | AB3: Month 27 | AC3: Month 28 | AD3: Month 29 | AE3: Month 30 | AF3: Month 31 | AG3: Month 32 | AH3: Month 33 | AI3: Month 34 | AJ3: Month 35 | AK3: Month 36 | AL3: Month 37 | AM3: Month 38 | AN3: Month 39 | AO3: Month 40 | AP3: Month 41 | AQ3: Month 42 | AR3: Month 43 | AS3: Month 44 | AT3: Month 45 | AU3: Month 46 | AV3: Month 47 | AW3: Month 48 | AX3: Month 49 | AY3: Month 50 | AZ3: Month 51 | BA3: Month 52 | BB3: Month 53 | BC3: Month 54 | BD3: Month 55 | BE3: Month 56 | BF3: Month 57 | BG3: Month 58 | BH3: Month 59 | BI3: Month 60
A4: =IF(COUNTA('Debt Tracker'!B4)>0,'Debt Tracker'!B4,"")
A5: =IF(COUNTA('Debt Tracker'!B5)>0,'Debt Tracker'!B5,"")
A6: =IF(COUNTA('Debt Tracker'!B6)>0,'Debt Tracker'!B6,"")
A7: =IF(COUNTA('Debt Tracker'!B7)>0,'Debt Tracker'!B7,"")
A8: =IF(COUNTA('Debt Tracker'!B8)>0,'Debt Tracker'!B8,"")
A9: =IF(COUNTA('Debt Tracker'!B9)>0,'Debt Tracker'!B9,"")
A10: =IF(COUNTA('Debt Tracker'!B10)>0,'Debt Tracker'!B10,"")
A11: =IF(COUNTA('Debt Tracker'!B11)>0,'Debt Tracker'!B11,"")
A12: =IF(COUNTA('Debt Tracker'!B12)>0,'Debt Tracker'!B12,"")
A13: =IF(COUNTA('Debt Tracker'!B13)>0,'Debt Tracker'!B13,"")
A14: =IF(COUNTA('Debt Tracker'!B14)>0,'Debt Tracker'!B14,"")
A15: =IF(COUNTA('Debt Tracker'!B15)>0,'Debt Tracker'!B15,"")
A17: Total Debt Remaining | B17: =SUM(B4:B16) -> 0 | C17: =SUM(C4:C16) -> 0 | D17: =SUM(D4:D16) -> 0 | E17: =SUM(E4:E16) -> 0 | F17: =SUM(F4:F16) -> 0 | G17: =SUM(G4:G16) -> 0 | H17: =SUM(H4:H16) -> 0 | I17: =SUM(I4:I16) -> 0 | ... BI17: =SUM(BI4:BI16) -> 0
A18: Monthly Interest Burn

Sheet Monthly Log
A1: Monthly Log
